{
  "project_info": {
    "project_number": "537779820545",
    "project_id": "digital-method-142715"
  },
  "client": [
    {
      "client_info": {
        "mobilesdk_app_id": "1:537779820545:android:95505dd0bc7de580",
        "android_client_info": {
          "package_name": "sunil.geotagged4"
        }
      },
      "oauth_client": [
        {
          "client_id": "537779820545-qm0iifhf64bv2qchru9sh63dljvgipqu.apps.googleusercontent.com",
          "client_type": 1,
          "android_info": {
            "package_name": "sunil.geotagged4",
            "certificate_hash": "75D9407548E66CD0271021AF14F813AFD4538424"
          }
        },
        {
          "client_id": "537779820545-faqu28rn7uf4tbg4bjmkfo55sevej996.apps.googleusercontent.com",
          "client_type": 3
        }
      ],
      "api_key": [
        {
          "current_key": "AIzaSyBfo34kAUe4IionGl5WkGxhOD0kHhAZJ1c"
        }
      ],
      "services": {
        "analytics_service": {
          "status": 1
        },
        "appinvite_service": {
          "status": 1,
          "other_platform_oauth_client": []
        },
        "ads_service": {
          "status": 1
        }
      }
    }
  ],
  "configuration_version": "1"
}